odoo8_addon_purchase_requisition_multicurrency-8.0.0.1.0.99.dev25-py3.8-nspkg.pth
odoo_addons/purchase_requisition_multicurrency/README.rst
odoo_addons/purchase_requisition_multicurrency/__init__.py
odoo_addons/purchase_requisition_multicurrency/__openerp__.py
odoo_addons/purchase_requisition_multicurrency/i18n/ca.po
odoo_addons/purchase_requisition_multicurrency/i18n/de.po
odoo_addons/purchase_requisition_multicurrency/i18n/el_GR.po
odoo_addons/purchase_requisition_multicurrency/i18n/es.po
odoo_addons/purchase_requisition_multicurrency/i18n/es_MX.po
odoo_addons/purchase_requisition_multicurrency/i18n/es_PE.po
odoo_addons/purchase_requisition_multicurrency/i18n/fi.po
odoo_addons/purchase_requisition_multicurrency/i18n/fr.po
odoo_addons/purchase_requisition_multicurrency/i18n/hr.po
odoo_addons/purchase_requisition_multicurrency/i18n/it.po
odoo_addons/purchase_requisition_multicurrency/i18n/nl_NL.po
odoo_addons/purchase_requisition_multicurrency/i18n/pt_BR.po
odoo_addons/purchase_requisition_multicurrency/i18n/pt_PT.po
odoo_addons/purchase_requisition_multicurrency/i18n/purchase_requisition_multicurrency.pot
odoo_addons/purchase_requisition_multicurrency/i18n/ro.po
odoo_addons/purchase_requisition_multicurrency/i18n/ru.po
odoo_addons/purchase_requisition_multicurrency/i18n/sl.po
odoo_addons/purchase_requisition_multicurrency/i18n/tr.po
odoo_addons/purchase_requisition_multicurrency/i18n/tr_TR.po
odoo_addons/purchase_requisition_multicurrency/model/__init__.py
odoo_addons/purchase_requisition_multicurrency/model/purchase_order.py
odoo_addons/purchase_requisition_multicurrency/model/purchase_requisition.py
odoo_addons/purchase_requisition_multicurrency/static/description/icon.png
odoo_addons/purchase_requisition_multicurrency/static/src/js/web_addons.js
odoo_addons/purchase_requisition_multicurrency/view/purchase_order.xml
odoo_addons/purchase_requisition_multicurrency/view/purchase_requisition.xml
odoo8_addon_purchase_requisition_multicurrency-8.0.0.1.0.99.dev25.dist-info/METADATA
odoo8_addon_purchase_requisition_multicurrency-8.0.0.1.0.99.dev25.dist-info/WHEEL
odoo8_addon_purchase_requisition_multicurrency-8.0.0.1.0.99.dev25.dist-info/namespace_packages.txt
odoo8_addon_purchase_requisition_multicurrency-8.0.0.1.0.99.dev25.dist-info/top_level.txt
odoo8_addon_purchase_requisition_multicurrency-8.0.0.1.0.99.dev25.dist-info/RECORD
